mjworker/__init__.py
mjworker/public.py
mjworker/publish.py
mjworker/sync.py
mjworker/task.py
mjworker/variables.py
mjworker/worker.py
mjworker-0.2.16.dist-info/METADATA
mjworker-0.2.16.dist-info/WHEEL
mjworker-0.2.16.dist-info/entry_points.txt
mjworker-0.2.16.dist-info/top_level.txt
mjworker-0.2.16.dist-info/RECORD
