Metadata-Version: 2.1
Name: mjworker
Version: 0.2.16
Summary: agent application for mj-monitor
Home-page: https://gitlab.dataenlighten.com/devops/monitor
Author: huyan
Author-email: lixiuhu_lee@163.com
License: UNKNOWN
Platform: UNKNOWN
Requires-Dist: Click
Requires-Dist: psutil
Requires-Dist: requests
